fractalartmaker/__init__.py
fractalartmaker/__main__.py
fractalartmaker-0.3.2.dist-info/METADATA
fractalartmaker-0.3.2.dist-info/WHEEL
fractalartmaker-0.3.2.dist-info/top_level.txt
fractalartmaker-0.3.2.dist-info/RECORD
